perception.libs/msvcp140-a4c2229bdc2a2a630acdc095b4d86008.dll
perception/__init__.py
perception/approximate_deduplication/__init__.py
perception/approximate_deduplication/debug.py
perception/approximate_deduplication/index.py
perception/approximate_deduplication/serve.py
perception/benchmarking/__init__.py
perception/benchmarking/common.py
perception/benchmarking/extensions.c
perception/benchmarking/extensions.cp310-win_amd64.pyd
perception/benchmarking/extensions.pyx
perception/benchmarking/image.py
perception/benchmarking/image_transforms.py
perception/benchmarking/video.py
perception/benchmarking/video_transforms.py
perception/extensions.cp310-win_amd64.pyd
perception/extensions.cpp
perception/extensions.pyx
perception/hashers/__init__.py
perception/hashers/hasher.py
perception/hashers/image/__init__.py
perception/hashers/image/average.py
perception/hashers/image/dhash.py
perception/hashers/image/opencv.py
perception/hashers/image/pdq.py
perception/hashers/image/phash.py
perception/hashers/image/wavelet.py
perception/hashers/tools.py
perception/hashers/video/__init__.py
perception/hashers/video/framewise.py
perception/hashers/video/tmk.py
perception/local_descriptor_deduplication.py
perception/py.typed
perception/testing/__init__.py
perception/testing/images/README.md
perception/testing/images/image1.jpg
perception/testing/images/image10.jpg
perception/testing/images/image2.jpg
perception/testing/images/image3.jpg
perception/testing/images/image4.jpg
perception/testing/images/image5.jpg
perception/testing/images/image6.jpg
perception/testing/images/image7.jpg
perception/testing/images/image8.jpg
perception/testing/images/image9.jpg
perception/testing/logos/README.md
perception/testing/logos/logoipsum.png
perception/testing/videos/README.md
perception/testing/videos/expected_tmk.json.gz
perception/testing/videos/rgb.m4v
perception/testing/videos/v1.m4v
perception/testing/videos/v2.m4v
perception/testing/videos/v2s.mov
perception/tools.py
perception/utils.py
perception-0.8.1.dist-info/DELVEWHEEL
perception-0.8.1.dist-info/LICENSE
perception-0.8.1.dist-info/METADATA
perception-0.8.1.dist-info/WHEEL
perception-0.8.1.dist-info/RECORD
